load_balancer/__init__.py
load_balancer/main.old.py
load_balancer/main.py
load_balancer/uds.py
load_balancer-0.1.1.dist-info/METADATA
load_balancer-0.1.1.dist-info/WHEEL
load_balancer-0.1.1.dist-info/top_level.txt
load_balancer-0.1.1.dist-info/RECORD
