Metadata-Version: 2.1
Name: load-balancer
Version: 0.1.1
Summary: Simple FastAPI load balancer
Author-email: Marcel Claramunt <marcel@moveread.com>
Project-URL: repo, https://github.com/moveread/REPO.git
Requires-Python: >=3.10
